{
  "personaId": "experienced",
  "seed": 1,
  "simulatedDays": 30,
  "startDate": "2026-05-17",
  "generatedAt": "2026-06-16T00:00:00.000Z",
  "summary": {
    "activeDays": 1,
    "totalSessions": 1,
    "totalLessons": 0,
    "totalEvents": 34,
    "finalOverallMastery": 89,
    "lessonMastery": {
      "review-1-1": {
        "lessonId": "review-1-1",
        "score": 100,
        "correctOnFirstTry": 1,
        "correctAfterHint": 0,
        "correctAfterReview": 0,
        "incorrect": 0,
        "totalAttempts": 1,
        "lastAttemptAt": "2026-05-17T07:00:04.217Z"
      },
      "review-1-2": {
        "lessonId": "review-1-2",
        "score": 100,
        "correctOnFirstTry": 1,
        "correctAfterHint": 0,
        "correctAfterReview": 0,
        "incorrect": 0,
        "totalAttempts": 1,
        "lastAttemptAt": "2026-05-17T07:00:12.964Z"
      },
      "review-1-3": {
        "lessonId": "review-1-3",
        "score": 100,
        "correctOnFirstTry": 1,
        "correctAfterHint": 0,
        "correctAfterReview": 0,
        "incorrect": 0,
        "totalAttempts": 1,
        "lastAttemptAt": "2026-05-17T07:00:23.334Z"
      },
      "review-2-1": {
        "lessonId": "review-2-1",
        "score": 100,
        "correctOnFirstTry": 1,
        "correctAfterHint": 0,
        "correctAfterReview": 0,
        "incorrect": 0,
        "totalAttempts": 1,
        "lastAttemptAt": "2026-05-17T07:00:41.275Z"
      },
      "review-2-2": {
        "lessonId": "review-2-2",
        "score": 100,
        "correctOnFirstTry": 1,
        "correctAfterHint": 0,
        "correctAfterReview": 0,
        "incorrect": 0,
        "totalAttempts": 1,
        "lastAttemptAt": "2026-05-17T07:00:54.537Z"
      },
      "review-2-3": {
        "lessonId": "review-2-3",
        "score": 100,
        "correctOnFirstTry": 1,
        "correctAfterHint": 0,
        "correctAfterReview": 0,
        "incorrect": 0,
        "totalAttempts": 1,
        "lastAttemptAt": "2026-05-17T07:01:02.353Z"
      },
      "review-3-1": {
        "lessonId": "review-3-1",
        "score": 100,
        "correctOnFirstTry": 1,
        "correctAfterHint": 0,
        "correctAfterReview": 0,
        "incorrect": 0,
        "totalAttempts": 1,
        "lastAttemptAt": "2026-05-17T07:01:13.976Z"
      },
      "review-3-2": {
        "lessonId": "review-3-2",
        "score": 100,
        "correctOnFirstTry": 1,
        "correctAfterHint": 0,
        "correctAfterReview": 0,
        "incorrect": 0,
        "totalAttempts": 1,
        "lastAttemptAt": "2026-05-17T07:01:23.050Z"
      },
      "review-3-3": {
        "lessonId": "review-3-3",
        "score": 0,
        "correctOnFirstTry": 0,
        "correctAfterHint": 0,
        "correctAfterReview": 0,
        "incorrect": 1,
        "totalAttempts": 1,
        "lastAttemptAt": "2026-05-17T07:01:32.619Z"
      }
    }
  },
  "events": [
    {
      "eventId": "sim_experienced_000001",
      "userId": "sim_experienced",
      "sessionId": null,
      "timestamp": "2026-05-17T07:00:00.000Z",
      "clientTimestamp": "2026-05-17T07:00:00.000Z",
      "sequenceNumber": 1,
      "kind": "app_opened",
      "source": "direct",
      "notificationId": null,
      "minutesSinceLastOpen": null,
      "localHourOfDay": 7,
      "localDayOfWeek": 6
    },
    {
      "eventId": "sim_experienced_000002",
      "userId": "sim_experienced",
      "sessionId": "sim_sess_experienced_0000",
      "timestamp": "2026-05-17T07:00:00.000Z",
      "clientTimestamp": "2026-05-17T07:00:00.000Z",
      "sequenceNumber": 2,
      "kind": "session_started",
      "resumedFromLessonId": null
    },
    {
      "eventId": "sim_experienced_000003",
      "userId": "sim_experienced",
      "sessionId": "sim_sess_experienced_0000",
      "timestamp": "2026-05-17T07:00:00.000Z",
      "clientTimestamp": "2026-05-17T07:00:00.000Z",
      "sequenceNumber": 3,
      "kind": "level_started",
      "levelId": "level-1",
      "isRestart": false
    },
    {
      "eventId": "sim_experienced_000004",
      "userId": "sim_experienced",
      "sessionId": "sim_sess_experienced_0000",
      "timestamp": "2026-05-17T07:00:00.000Z",
      "clientTimestamp": "2026-05-17T07:00:00.000Z",
      "sequenceNumber": 4,
      "kind": "level_review_started",
      "levelId": "level-1",
      "reviewId": "review-1",
      "triggeredBy": "directive"
    },
    {
      "eventId": "sim_experienced_000005",
      "userId": "sim_experienced",
      "sessionId": "sim_sess_experienced_0000",
      "timestamp": "2026-05-17T07:00:00.000Z",
      "clientTimestamp": "2026-05-17T07:00:00.000Z",
      "sequenceNumber": 5,
      "kind": "review_card_shown",
      "levelId": "level-1",
      "reviewId": "review-1",
      "lessonId": "review-1-1",
      "cardOrder": 1
    },
    {
      "eventId": "sim_experienced_000006",
      "userId": "sim_experienced",
      "sessionId": "sim_sess_experienced_0000",
      "timestamp": "2026-05-17T07:00:04.217Z",
      "clientTimestamp": "2026-05-17T07:00:04.217Z",
      "sequenceNumber": 6,
      "kind": "review_answer_submitted",
      "levelId": "level-1",
      "reviewId": "review-1",
      "lessonId": "review-1-1",
      "questionFormat": "multiple_choice",
      "selectedOptionId": "b",
      "selectedBooleanAnswer": null,
      "isCorrect": true,
      "hintUsed": false,
      "answerLatencyMs": 4217
    },
    {
      "eventId": "sim_experienced_000007",
      "userId": "sim_experienced",
      "sessionId": "sim_sess_experienced_0000",
      "timestamp": "2026-05-17T07:00:10.866Z",
      "clientTimestamp": "2026-05-17T07:00:10.866Z",
      "sequenceNumber": 7,
      "kind": "review_card_shown",
      "levelId": "level-1",
      "reviewId": "review-1",
      "lessonId": "review-1-2",
      "cardOrder": 2
    },
    {
      "eventId": "sim_experienced_000008",
      "userId": "sim_experienced",
      "sessionId": "sim_sess_experienced_0000",
      "timestamp": "2026-05-17T07:00:12.964Z",
      "clientTimestamp": "2026-05-17T07:00:12.964Z",
      "sequenceNumber": 8,
      "kind": "review_answer_submitted",
      "levelId": "level-1",
      "reviewId": "review-1",
      "lessonId": "review-1-2",
      "questionFormat": "true_false",
      "selectedOptionId": null,
      "selectedBooleanAnswer": true,
      "isCorrect": true,
      "hintUsed": false,
      "answerLatencyMs": 2098
    },
    {
      "eventId": "sim_experienced_000009",
      "userId": "sim_experienced",
      "sessionId": "sim_sess_experienced_0000",
      "timestamp": "2026-05-17T07:00:18.800Z",
      "clientTimestamp": "2026-05-17T07:00:18.800Z",
      "sequenceNumber": 9,
      "kind": "review_card_shown",
      "levelId": "level-1",
      "reviewId": "review-1",
      "lessonId": "review-1-3",
      "cardOrder": 3
    },
    {
      "eventId": "sim_experienced_000010",
      "userId": "sim_experienced",
      "sessionId": "sim_sess_experienced_0000",
      "timestamp": "2026-05-17T07:00:23.334Z",
      "clientTimestamp": "2026-05-17T07:00:23.334Z",
      "sequenceNumber": 10,
      "kind": "review_answer_submitted",
      "levelId": "level-1",
      "reviewId": "review-1",
      "lessonId": "review-1-3",
      "questionFormat": "multiple_choice",
      "selectedOptionId": "a",
      "selectedBooleanAnswer": null,
      "isCorrect": true,
      "hintUsed": false,
      "answerLatencyMs": 4534
    },
    {
      "eventId": "sim_experienced_000011",
      "userId": "sim_experienced",
      "sessionId": "sim_sess_experienced_0000",
      "timestamp": "2026-05-17T07:00:28.878Z",
      "clientTimestamp": "2026-05-17T07:00:28.878Z",
      "sequenceNumber": 11,
      "kind": "level_review_completed",
      "levelId": "level-1",
      "reviewId": "review-1",
      "passed": true,
      "durationMs": 28878,
      "masteryScoreAfter": 100
    },
    {
      "eventId": "sim_experienced_000012",
      "userId": "sim_experienced",
      "sessionId": "sim_sess_experienced_0000",
      "timestamp": "2026-05-17T07:00:28.878Z",
      "clientTimestamp": "2026-05-17T07:00:28.878Z",
      "sequenceNumber": 12,
      "kind": "level_completed",
      "levelId": "level-1",
      "masteryScore": 100,
      "durationMs": 28878,
      "lessonsCompleted": 0,
      "lessonsSkipped": 4
    },
    {
      "eventId": "sim_experienced_000013",
      "userId": "sim_experienced",
      "sessionId": "sim_sess_experienced_0000",
      "timestamp": "2026-05-17T07:00:33.389Z",
      "clientTimestamp": "2026-05-17T07:00:33.389Z",
      "sequenceNumber": 13,
      "kind": "level_started",
      "levelId": "level-2",
      "isRestart": false
    },
    {
      "eventId": "sim_experienced_000014",
      "userId": "sim_experienced",
      "sessionId": "sim_sess_experienced_0000",
      "timestamp": "2026-05-17T07:00:33.389Z",
      "clientTimestamp": "2026-05-17T07:00:33.389Z",
      "sequenceNumber": 14,
      "kind": "level_review_started",
      "levelId": "level-2",
      "reviewId": "review-2",
      "triggeredBy": "directive"
    },
    {
      "eventId": "sim_experienced_000015",
      "userId": "sim_experienced",
      "sessionId": "sim_sess_experienced_0000",
      "timestamp": "2026-05-17T07:00:33.389Z",
      "clientTimestamp": "2026-05-17T07:00:33.389Z",
      "sequenceNumber": 15,
      "kind": "review_card_shown",
      "levelId": "level-2",
      "reviewId": "review-2",
      "lessonId": "review-2-1",
      "cardOrder": 1
    },
    {
      "eventId": "sim_experienced_000016",
      "userId": "sim_experienced",
      "sessionId": "sim_sess_experienced_0000",
      "timestamp": "2026-05-17T07:00:41.275Z",
      "clientTimestamp": "2026-05-17T07:00:41.275Z",
      "sequenceNumber": 16,
      "kind": "review_answer_submitted",
      "levelId": "level-2",
      "reviewId": "review-2",
      "lessonId": "review-2-1",
      "questionFormat": "true_false",
      "selectedOptionId": null,
      "selectedBooleanAnswer": false,
      "isCorrect": true,
      "hintUsed": false,
      "answerLatencyMs": 7886
    },
    {
      "eventId": "sim_experienced_000017",
      "userId": "sim_experienced",
      "sessionId": "sim_sess_experienced_0000",
      "timestamp": "2026-05-17T07:00:48.441Z",
      "clientTimestamp": "2026-05-17T07:00:48.441Z",
      "sequenceNumber": 17,
      "kind": "review_card_shown",
      "levelId": "level-2",
      "reviewId": "review-2",
      "lessonId": "review-2-2",
      "cardOrder": 2
    },
    {
      "eventId": "sim_experienced_000018",
      "userId": "sim_experienced",
      "sessionId": "sim_sess_experienced_0000",
      "timestamp": "2026-05-17T07:00:54.537Z",
      "clientTimestamp": "2026-05-17T07:00:54.537Z",
      "sequenceNumber": 18,
      "kind": "review_answer_submitted",
      "levelId": "level-2",
      "reviewId": "review-2",
      "lessonId": "review-2-2",
      "questionFormat": "multiple_choice",
      "selectedOptionId": "b",
      "selectedBooleanAnswer": null,
      "isCorrect": true,
      "hintUsed": false,
      "answerLatencyMs": 6096
    },
    {
      "eventId": "sim_experienced_000019",
      "userId": "sim_experienced",
      "sessionId": "sim_sess_experienced_0000",
      "timestamp": "2026-05-17T07:00:59.726Z",
      "clientTimestamp": "2026-05-17T07:00:59.726Z",
      "sequenceNumber": 19,
      "kind": "review_card_shown",
      "levelId": "level-2",
      "reviewId": "review-2",
      "lessonId": "review-2-3",
      "cardOrder": 3
    },
    {
      "eventId": "sim_experienced_000020",
      "userId": "sim_experienced",
      "sessionId": "sim_sess_experienced_0000",
      "timestamp": "2026-05-17T07:01:02.353Z",
      "clientTimestamp": "2026-05-17T07:01:02.353Z",
      "sequenceNumber": 20,
      "kind": "review_answer_submitted",
      "levelId": "level-2",
      "reviewId": "review-2",
      "lessonId": "review-2-3",
      "questionFormat": "true_false",
      "selectedOptionId": null,
      "selectedBooleanAnswer": false,
      "isCorrect": true,
      "hintUsed": false,
      "answerLatencyMs": 2627
    },
    {
      "eventId": "sim_experienced_000021",
      "userId": "sim_experienced",
      "sessionId": "sim_sess_experienced_0000",
      "timestamp": "2026-05-17T07:01:04.776Z",
      "clientTimestamp": "2026-05-17T07:01:04.776Z",
      "sequenceNumber": 21,
      "kind": "level_review_completed",
      "levelId": "level-2",
      "reviewId": "review-2",
      "passed": true,
      "durationMs": 31387,
      "masteryScoreAfter": 100
    },
    {
      "eventId": "sim_experienced_000022",
      "userId": "sim_experienced",
      "sessionId": "sim_sess_experienced_0000",
      "timestamp": "2026-05-17T07:01:04.776Z",
      "clientTimestamp": "2026-05-17T07:01:04.776Z",
      "sequenceNumber": 22,
      "kind": "level_completed",
      "levelId": "level-2",
      "masteryScore": 100,
      "durationMs": 31387,
      "lessonsCompleted": 0,
      "lessonsSkipped": 4
    },
    {
      "eventId": "sim_experienced_000023",
      "userId": "sim_experienced",
      "sessionId": "sim_sess_experienced_0000",
      "timestamp": "2026-05-17T07:01:07.732Z",
      "clientTimestamp": "2026-05-17T07:01:07.732Z",
      "sequenceNumber": 23,
      "kind": "level_started",
      "levelId": "level-3",
      "isRestart": false
    },
    {
      "eventId": "sim_experienced_000024",
      "userId": "sim_experienced",
      "sessionId": "sim_sess_experienced_0000",
      "timestamp": "2026-05-17T07:01:07.732Z",
      "clientTimestamp": "2026-05-17T07:01:07.732Z",
      "sequenceNumber": 24,
      "kind": "level_review_started",
      "levelId": "level-3",
      "reviewId": "review-3",
      "triggeredBy": "directive"
    },
    {
      "eventId": "sim_experienced_000025",
      "userId": "sim_experienced",
      "sessionId": "sim_sess_experienced_0000",
      "timestamp": "2026-05-17T07:01:07.732Z",
      "clientTimestamp": "2026-05-17T07:01:07.732Z",
      "sequenceNumber": 25,
      "kind": "review_card_shown",
      "levelId": "level-3",
      "reviewId": "review-3",
      "lessonId": "review-3-1",
      "cardOrder": 1
    },
    {
      "eventId": "sim_experienced_000026",
      "userId": "sim_experienced",
      "sessionId": "sim_sess_experienced_0000",
      "timestamp": "2026-05-17T07:01:13.976Z",
      "clientTimestamp": "2026-05-17T07:01:13.976Z",
      "sequenceNumber": 26,
      "kind": "review_answer_submitted",
      "levelId": "level-3",
      "reviewId": "review-3",
      "lessonId": "review-3-1",
      "questionFormat": "multiple_choice",
      "selectedOptionId": "b",
      "selectedBooleanAnswer": null,
      "isCorrect": true,
      "hintUsed": false,
      "answerLatencyMs": 6244
    },
    {
      "eventId": "sim_experienced_000027",
      "userId": "sim_experienced",
      "sessionId": "sim_sess_experienced_0000",
      "timestamp": "2026-05-17T07:01:19.473Z",
      "clientTimestamp": "2026-05-17T07:01:19.473Z",
      "sequenceNumber": 27,
      "kind": "review_card_shown",
      "levelId": "level-3",
      "reviewId": "review-3",
      "lessonId": "review-3-2",
      "cardOrder": 2
    },
    {
      "eventId": "sim_experienced_000028",
      "userId": "sim_experienced",
      "sessionId": "sim_sess_experienced_0000",
      "timestamp": "2026-05-17T07:01:23.050Z",
      "clientTimestamp": "2026-05-17T07:01:23.050Z",
      "sequenceNumber": 28,
      "kind": "review_answer_submitted",
      "levelId": "level-3",
      "reviewId": "review-3",
      "lessonId": "review-3-2",
      "questionFormat": "true_false",
      "selectedOptionId": null,
      "selectedBooleanAnswer": true,
      "isCorrect": true,
      "hintUsed": false,
      "answerLatencyMs": 3577
    },
    {
      "eventId": "sim_experienced_000029",
      "userId": "sim_experienced",
      "sessionId": "sim_sess_experienced_0000",
      "timestamp": "2026-05-17T07:01:29.556Z",
      "clientTimestamp": "2026-05-17T07:01:29.556Z",
      "sequenceNumber": 29,
      "kind": "review_card_shown",
      "levelId": "level-3",
      "reviewId": "review-3",
      "lessonId": "review-3-3",
      "cardOrder": 3
    },
    {
      "eventId": "sim_experienced_000030",
      "userId": "sim_experienced",
      "sessionId": "sim_sess_experienced_0000",
      "timestamp": "2026-05-17T07:01:32.619Z",
      "clientTimestamp": "2026-05-17T07:01:32.619Z",
      "sequenceNumber": 30,
      "kind": "review_answer_submitted",
      "levelId": "level-3",
      "reviewId": "review-3",
      "lessonId": "review-3-3",
      "questionFormat": "true_false",
      "selectedOptionId": null,
      "selectedBooleanAnswer": true,
      "isCorrect": false,
      "hintUsed": false,
      "answerLatencyMs": 3063
    },
    {
      "eventId": "sim_experienced_000031",
      "userId": "sim_experienced",
      "sessionId": "sim_sess_experienced_0000",
      "timestamp": "2026-05-17T07:01:36.624Z",
      "clientTimestamp": "2026-05-17T07:01:36.624Z",
      "sequenceNumber": 31,
      "kind": "level_review_completed",
      "levelId": "level-3",
      "reviewId": "review-3",
      "passed": false,
      "durationMs": 28892,
      "masteryScoreAfter": 89
    },
    {
      "eventId": "sim_experienced_000032",
      "userId": "sim_experienced",
      "sessionId": "sim_sess_experienced_0000",
      "timestamp": "2026-05-17T07:01:36.624Z",
      "clientTimestamp": "2026-05-17T07:01:36.624Z",
      "sequenceNumber": 32,
      "kind": "level_completed",
      "levelId": "level-3",
      "masteryScore": 89,
      "durationMs": 28892,
      "lessonsCompleted": 0,
      "lessonsSkipped": 4
    },
    {
      "eventId": "sim_experienced_000033",
      "userId": "sim_experienced",
      "sessionId": "sim_sess_experienced_0000",
      "timestamp": "2026-05-17T07:01:41.574Z",
      "clientTimestamp": "2026-05-17T07:01:41.574Z",
      "sequenceNumber": 33,
      "kind": "session_ended",
      "durationMs": 101574,
      "reason": "completed",
      "lessonsAttempted": 3,
      "lessonsCompleted": 2,
      "overallMasteryAtEnd": 89
    },
    {
      "eventId": "sim_experienced_000034",
      "userId": "sim_experienced",
      "sessionId": null,
      "timestamp": "2026-05-17T07:01:41.574Z",
      "clientTimestamp": "2026-05-17T07:01:41.574Z",
      "sequenceNumber": 34,
      "kind": "app_backgrounded",
      "foregroundDurationMs": 101574
    }
  ]
}